{"id":"17346db7-2c19-4f5f-9454-9addbc15df3e","revision":0,"last_node_id":243,"last_link_id":356,"nodes":[{"id":227,"type":"SaveImage","pos":[-402.3359069824219,704.1817016601562],"size":[270,270],"flags":{},"order":6,"mode":0,"inputs":[{"localized_name":"images","name":"images","type":"IMAGE","link":325},{"localized_name":"filename_prefix","name":"filename_prefix","type":"STRING","widget":{"name":"filename_prefix"},"link":null}],"outputs":[],"properties":{"cnr_id":"comfy-core","ver":"0.3.39","Node name for S&R":"SaveImage","widget_ue_connectable":{}},"widgets_values":["SBS"]},{"id":232,"type":"DepthAnything_V2","pos":[-1005.2589721679688,801.8712158203125],"size":[156.64413452148438,46],"flags":{},"order":4,"mode":0,"inputs":[{"localized_name":"da_model","name":"da_model","type":"DAMODEL","link":336},{"localized_name":"images","name":"images","type":"IMAGE","link":349}],"outputs":[{"localized_name":"image","name":"image","type":"IMAGE","links":[337]}],"properties":{"Node name for S&R":"DepthAnything_V2","cnr_id":"comfyui-depthanythingv2","ver":"1.0.1","widget_ue_connectable":{}},"widgets_values":[]},{"id":233,"type":"DownloadAndLoadDepthAnythingV2Model","pos":[-1300.4278564453125,980.8600463867188],"size":[365.3121032714844,82],"flags":{},"order":0,"mode":0,"inputs":[{"localized_name":"model","name":"model","type":"COMBO","widget":{"name":"model"},"link":null},{"localized_name":"precision","name":"precision","shape":7,"type":"COMBO","widget":{"name":"precision"},"link":null}],"outputs":[{"localized_name":"da_v2_model","name":"da_v2_model","type":"DAMODEL","links":[336]}],"properties":{"Node name for S&R":"DownloadAndLoadDepthAnythingV2Model","cnr_id":"comfyui-depthanythingv2","ver":"1.0.1","widget_ue_connectable":{}},"widgets_values":["depth_anything_v2_vitb_fp16.safetensors","auto"]},{"id":239,"type":"ScaleToResolution","pos":[-1309.710205078125,822.1864624023438],"size":[270,106],"flags":{},"order":3,"mode":0,"inputs":[{"localized_name":"image","name":"image","type":"IMAGE","link":355},{"localized_name":"resolution","name":"resolution","type":"INT","widget":{"name":"resolution"},"link":null},{"localized_name":"algorithm","name":"algorithm","type":"COMBO","widget":{"name":"algorithm"},"link":null},{"localized_name":"roundexponent","name":"roundexponent","type":"INT","widget":{"name":"roundexponent"},"link":null}],"outputs":[{"localized_name":"result","name":"result","type":"IMAGE","links":[349]}],"properties":{"cnr_id":"comfyui_stereoscopic","ver":"76fee884224e63a6669050171a85097a715c38bf","Node name for S&R":"ScaleToResolution","widget_ue_connectable":{}},"widgets_values":[1024,"INTER_AREA",4]},{"id":220,"type":"ImageVRConverter","pos":[-750.271240234375,705.042724609375],"size":[277.1015625,222],"flags":{},"order":5,"mode":0,"inputs":[{"localized_name":"base_image","name":"base_image","type":"IMAGE","link":356},{"localized_name":"depth_image","name":"depth_image","type":"IMAGE","link":337},{"localized_name":"depth_scale","name":"depth_scale","type":"FLOAT","widget":{"name":"depth_scale"},"link":null},{"localized_name":"depth_offset","name":"depth_offset","type":"FLOAT","widget":{"name":"depth_offset"},"link":null},{"localized_name":"switch_sides","name":"switch_sides","type":"BOOLEAN","widget":{"name":"switch_sides"},"link":null},{"localized_name":"blur_radius","name":"blur_radius","type":"INT","widget":{"name":"blur_radius"},"link":null},{"localized_name":"symetric","name":"symetric","type":"BOOLEAN","widget":{"name":"symetric"},"link":null},{"localized_name":"processing","name":"processing","type":"COMBO","widget":{"name":"processing"},"link":null}],"outputs":[{"localized_name":"stereoscopic_image","name":"stereoscopic_image","type":"IMAGE","links":[325]}],"properties":{"cnr_id":"comfyui_stereoscopic","ver":"5bc7af9f2b51025524e142140ef9aa427d1fa8ee","Node name for S&R":"ImageVRConverter","aux_id":"FortunaCournot/comfyui_stereoscopic","widget_ue_connectable":{}},"widgets_values":[1.2000000000000002,0,false,19,true,"Normal"]},{"id":231,"type":"Note","pos":[-1664.779541015625,538.5845336914062],"size":[311.4583740234375,88],"flags":{},"order":2,"mode":0,"inputs":[],"outputs":[],"title":"Custom node Dependencies","properties":{"widget_ue_connectable":{}},"widgets_values":["\ncomfyui_stereoscopic\ncomfyui-depthanythingv2\n"],"color":"#432","bgcolor":"#653"},{"id":243,"type":"Load image with metadata [Crystools]","pos":[-1677.8265380859375,762.1799926757812],"size":[287.2251892089844,354.00006103515625],"flags":{},"order":1,"mode":0,"inputs":[{"localized_name":"image","name":"image","type":"COMBO","widget":{"name":"image"},"link":null},{"localized_name":"upload","name":"upload","type":"IMAGEUPLOAD","widget":{"name":"upload"},"link":null}],"outputs":[{"localized_name":"image","name":"image","type":"IMAGE","links":[355,356]},{"localized_name":"mask","name":"mask","type":"MASK","links":null},{"localized_name":"prompt","name":"prompt","type":"JSON","links":null},{"localized_name":"Metadata RAW","name":"Metadata RAW","type":"METADATA_RAW","links":null}],"title":"Load image with metadata","properties":{"Node name for S&R":"Load image with metadata [Crystools]"},"widgets_values":["vr/samples/Teacher_00152_1k.jpg","image"]}],"links":[[325,220,0,227,0,"IMAGE"],[336,233,0,232,0,"DAMODEL"],[337,232,0,220,1,"IMAGE"],[349,239,0,232,1,"IMAGE"],[355,243,0,239,0,"IMAGE"],[356,243,0,220,0,"IMAGE"]],"groups":[],"config":{},"extra":{"ds":{"scale":1.2284597357367344,"offset":[1751.3967773115965,-450.9434539843408]},"reroutes":[{"id":1,"pos":[-1343.95751953125,781.4420776367188],"linkIds":[355,356]}],"ue_links":[],"links_added_by_ue":[],"linkExtensions":[{"id":355,"parentId":1},{"id":356,"parentId":1}]},"version":0.4}